webXtools/__init__.py
webXtools/bf.py
webXtools/helper.py
webXtools/jwthax.py
webXtools/race.py
webXtools-1.2.0.dist-info/METADATA
webXtools-1.2.0.dist-info/WHEEL
webXtools-1.2.0.dist-info/top_level.txt
webXtools-1.2.0.dist-info/RECORD
