Metadata-Version: 2.1
Name: webXtools
Version: 1.2.0
Summary: A set of tools for Web Exploitation
Author: Az3z3l (Yaswant)
Author-email: <star7ricks@gmail.com>
Keywords: python,hacking,ctf,web explotation,bruteforce
Classifier: Development Status :: 3 - Alpha
Classifier: Intended Audience :: Developers
Classifier: Intended Audience :: Education
Classifier: Programming Language :: Python :: 3
Classifier: Operating System :: Unix
Classifier: Operating System :: MacOS :: MacOS X
Classifier: Operating System :: Microsoft :: Windows
Requires-Dist: asyncio
